slavkopy/__init__.py
slavkopy/code.py
slavkopy-1.7.dist-info/METADATA
slavkopy-1.7.dist-info/WHEEL
slavkopy-1.7.dist-info/top_level.txt
slavkopy-1.7.dist-info/RECORD
