Metadata-Version: 2.1
Name: slavkopy
Version: 1.7
Summary: slavko.boy
Home-page: https://github.com/slavkomelnyk/slavkopy
Author: slavko.boy
Author-email: hello.slavko.melnyk@gmail.com
Classifier: Operating System :: MacOS :: MacOS X
Classifier: Operating System :: Microsoft :: Windows
Classifier: Programming Language :: Python
Classifier: Topic :: Communications :: Email
Requires-Dist: setuptools
